quickconn/__init__.py
quickconn/cloudflare.py
quickconn/http_clients.py
quickconn-0.2.0.dist-info/METADATA
quickconn-0.2.0.dist-info/WHEEL
quickconn-0.2.0.dist-info/top_level.txt
quickconn-0.2.0.dist-info/RECORD
