Metadata-Version: 2.4
Name: quickconn
Version: 0.2.0
Summary: Unified HTTP clients: HTTP/1.0, HTTP/1.1, HTTP/2, HTTP/3 and Cloudflare solver
Home-page: https://github.com/Gisnsl/QuickConn
Author: أحمد الحراني
Author-email: alhranyahmed@gmail.com
License: MIT
Keywords: http http1 http2 http3 cloudscraper client requests
Classifier: Programming Language :: Python :: 3
Classifier: License :: OSI Approved :: MIT License
Classifier: Operating System :: OS Independent
Requires-Python: >=3.9
Requires-Dist: httpx
Requires-Dist: aioquic
Requires-Dist: cloudscraper
Dynamic: author
Dynamic: author-email
Dynamic: classifier
Dynamic: description
Dynamic: description-content-type
Dynamic: home-page
Dynamic: keywords
Dynamic: license
Dynamic: requires-dist
Dynamic: requires-python
Dynamic: summary
